readimc/__init__.py
readimc/_version.py
readimc/imc_file.py
readimc/mcd_file.py
readimc/mcd_parser.py
readimc/txt_file.py
readimc/data/__init__.py
readimc/data/acquisition.py
readimc/data/panorama.py
readimc/data/slide.py
readimc-0.9.2.dist-info/licenses/AUTHORS.md
readimc-0.9.2.dist-info/licenses/LICENSE
readimc-0.9.2.dist-info/METADATA
readimc-0.9.2.dist-info/WHEEL
readimc-0.9.2.dist-info/top_level.txt
readimc-0.9.2.dist-info/RECORD
