Metadata-Version: 2.4
Name: readimc
Version: 0.9.2
Summary: Python package for reading IMC files
Requires-Python: >=3.8
License-File: LICENSE
License-File: AUTHORS.md
Dynamic: license-file
